testsolar_testtool_sdk/__init__.py
testsolar_testtool_sdk/file_reader.py
testsolar_testtool_sdk/pipe_reader.py
testsolar_testtool_sdk/py.typed
testsolar_testtool_sdk/reporter.py
testsolar_testtool_sdk/model/__init__.py
testsolar_testtool_sdk/model/encoder.py
testsolar_testtool_sdk/model/load.py
testsolar_testtool_sdk/model/param.py
testsolar_testtool_sdk/model/test.py
testsolar_testtool_sdk/model/testresult.py
testsolar_testtool_sdk-0.4.5.dist-info/METADATA
testsolar_testtool_sdk-0.4.5.dist-info/WHEEL
testsolar_testtool_sdk-0.4.5.dist-info/licenses/LICENSE
testsolar_testtool_sdk-0.4.5.dist-info/RECORD
