Metadata-Version: 2.4
Name: testsolar-testtool-sdk
Version: 0.4.5
Summary: Python3 SDK for TestSolar testtool
Project-URL: repository, https://github.com/OpenTestSolar/testtool-sdk-python
Author-email: asiazhang <asiazhang2002@gmail.com>
License: Apache License 2.0
License-File: LICENSE
Keywords: testsolar
Classifier: Development Status :: 4 - Beta
Classifier: Intended Audience :: Developers
Classifier: Programming Language :: Python
Classifier: Programming Language :: Python :: 3
Classifier: Programming Language :: Python :: 3.7
Classifier: Programming Language :: Python :: 3.8
Classifier: Programming Language :: Python :: 3.9
Classifier: Programming Language :: Python :: 3.10
Classifier: Programming Language :: Python :: 3.11
Classifier: Programming Language :: Python :: 3.12
Requires-Python: >=3.7
Requires-Dist: dacite>=1.8.1
Requires-Dist: portalocker>=2.7
